dokr_pkg/__init__.py
dokr_pkg/anonymous_matlab.py
dokr_pkg/try1.py
dokr_pkg/vit2.py
vit2.py-0.1.data/scripts/abc_matlab.py
vit2.py-0.1.data/scripts/anonymous_matlab.py
vit2.py-0.1.data/scripts/try1.py
vit2.py-0.1.data/scripts/vit1.py
vit2.py-0.1.data/scripts/vit2.py
vit2.py-0.1.dist-info/METADATA
vit2.py-0.1.dist-info/WHEEL
vit2.py-0.1.dist-info/top_level.txt
vit2.py-0.1.dist-info/RECORD
